{"airfield-11":{"height":17,"pixelRatio":1,"width":17,"x":147,"y":353},"airfield-15":{"height":21,"pixelRatio":1,"width":21,"x":214,"y":216},"airport-11":{"height":17,"pixelRatio":1,"width":17,"x":387,"y":50},"airport-15":{"height":21,"pixelRatio":1,"width":21,"x":237,"y":215},"alcohol-shop-11":{"height":19,"pixelRatio":1,"width":19,"x":146,"y":372},"alcohol-shop-15":{"height":23,"pixelRatio":1,"width":23,"x":2,"y":409},"amusement-park-11":{"height":19,"pixelRatio":1,"width":19,"x":239,"y":238},"amusement-park-15":{"height":23,"pixelRatio":1,"width":23,"x":2,"y":434},"aquarium-11":{"height":19,"pixelRatio":1,"width":19,"x":241,"y":259},"aquarium-15":{"height":23,"pixelRatio":1,"width":23,"x":2,"y":459},"art-gallery-11":{"height":19,"pixelRatio":1,"width":19,"x":241,"y":280},"art-gallery-15":{"height":23,"pixelRatio":1,"width":23,"x":21,"y":374},"attraction-11":{"height":19,"pixelRatio":1,"width":19,"x":191,"y":312},"attraction-15":{"height":23,"pixelRatio":1,"width":23,"x":412,"y":18},"bakery-11":{"height":19,"pixelRatio":1,"width":19,"x":191,"y":333},"bakery-15":{"height":23,"pixelRatio":1,"width":23,"x":82,"y":154},"bank-11":{"height":19,"pixelRatio":1,"width":19,"x":242,"y":301},"bank-15":{"height":23,"pixelRatio":1,"width":23,"x":82,"y":179},"bar-11":{"height":19,"pixelRatio":1,"width":19,"x":242,"y":322},"bar-15":{"height":23,"pixelRatio":1,"width":23,"x":82,"y":204},"barcelona-metro":{"height":17,"pixelRatio":1,"width":20,"x":125,"y":122},"beer-11":{"height":19,"pixelRatio":1,"width":19,"x":192,"y":354},"beer-15":{"height":23,"pixelRatio":1,"width":23,"x":82,"y":229},"bicycle-11":{"height":19,"pixelRatio":1,"width":19,"x":243,"y":343},"bicycle-15":{"height":23,"pixelRatio":1,"width":23,"x":107,"y":154},"bicycle-share-11":{"height":19,"pixelRatio":1,"width":19,"x":243,"y":364},"bicycle-share-15":{"height":23,"pixelRatio":1,"width":23,"x":107,"y":179},"blue_1":{"height":14,"pixelRatio":1,"width":14,"x":76,"y":312},"blue_2":{"height":14,"pixelRatio":1,"width":18,"x":105,"y":353},"blue_3":{"height":14,"pixelRatio":1,"width":23,"x":27,"y":474},"blue_4":{"height":14,"pixelRatio":1,"width":28,"x":75,"y":353},"blue_5":{"height":14,"pixelRatio":1,"width":32,"x":437,"y":35},"blue_6":{"height":14,"pixelRatio":1,"width":37,"x":52,"y":120},"blue_circle_1":{"height":14,"pixelRatio":1,"width":15,"x":115,"y":270},"blue_circle_2":{"height":14,"pixelRatio":1,"width":20,"x":125,"y":353},"blue_circle_3":{"height":14,"pixelRatio":1,"width":25,"x":471,"y":35},"blue_circle_4":{"height":14,"pixelRatio":1,"width":30,"x":116,"y":254},"blue_circle_5":{"height":14,"pixelRatio":1,"width":35,"x":297,"y":22},"blue_circle_6":{"height":14,"pixelRatio":1,"width":40,"x":61,"y":56},"blue_penta_1":{"height":14,"pixelRatio":1,"width":14,"x":460,"y":136},"blue_penta_2":{"height":14,"pixelRatio":1,"width":18,"x":191,"y":296},"blue_penta_3":{"height":14,"pixelRatio":1,"width":23,"x":132,"y":270},"blue_penta_4":{"height":14,"pixelRatio":1,"width":28,"x":214,"y":150},"blue_penta_5":{"height":14,"pixelRatio":1,"width":32,"x":91,"y":122},"blue_penta_6":{"height":14,"pixelRatio":1,"width":37,"x":50,"y":136},"blue_rnd_sqr_shield_1":{"height":14,"pixelRatio":1,"width":14,"x":460,"y":218},"blue_rnd_sqr_shield_2":{"height":14,"pixelRatio":1,"width":18,"x":288,"y":413},"blue_rnd_sqr_shield_3":{"height":14,"pixelRatio":1,"width":23,"x":214,"y":239},"blue_rnd_sqr_shield_4":{"height":14,"pixelRatio":1,"width":28,"x":181,"y":280},"blue_rnd_sqr_shield_5":{"height":14,"pixelRatio":1,"width":32,"x":89,"y":138},"blue_rnd_sqr_shield_6":{"height":14,"pixelRatio":1,"width":37,"x":43,"y":152},"blue_rnd_triangle_1":{"height":14,"pixelRatio":1,"width":13,"x":460,"y":448},"blue_rnd_triangle_2":{"height":14,"pixelRatio":1,"width":17,"x":285,"y":450},"blue_rnd_triangle_3":{"height":14,"pixelRatio":1,"width":22,"x":382,"y":69},"blue_rnd_triangle_4":{"height":14,"pixelRatio":1,"width":26,"x":211,"y":255},"blue_rnd_triangle_5":{"height":14,"pixelRatio":1,"width":31,"x":147,"y":134},"blue_rnd_triangle_6":{"height":14,"pixelRatio":1,"width":35,"x":105,"y":42},"blue_sixtangle90_1":{"height":14,"pixelRatio":1,"width":18,"x":327,"y":450},"blue_sixtangle90_2":{"height":14,"pixelRatio":1,"width":24,"x":472,"y":19},"blue_sixtangle90_3":{"height":14,"pixelRatio":1,"width":30,"x":182,"y":216},"blue_sixtangle90_4":{"height":14,"pixelRatio":1,"width":36,"x":142,"y":54},"blue_sixtangle90_5":{"height":14,"pixelRatio":1,"width":42,"x":61,"y":40},"blue_sixtangle90_6":{"height":14,"pixelRatio":1,"width":48,"x":2,"y":120},"blue_sixtangle_1":{"height":14,"pixelRatio":1,"width":14,"x":460,"y":234},"blue_sixtangle_2":{"height":14,"pixelRatio":1,"width":18,"x":388,"y":351},"blue_sixtangle_3":{"height":14,"pixelRatio":1,"width":23,"x":381,"y":85},"blue_sixtangle_4":{"height":14,"pixelRatio":1,"width":28,"x":211,"y":271},"blue_sixtangle_5":{"height":14,"pixelRatio":1,"width":32,"x":82,"y":254},"blue_sixtangle_6":{"height":14,"pixelRatio":1,"width":37,"x":43,"y":168},"blue_str_penta_1":{"height":14,"pixelRatio":1,"width":12,"x":311,"y":134},"blue_str_penta_2":{"height":14,"pixelRatio":1,"width":16,"x":416,"y":195},"blue_str_penta_3":{"height":14,"pixelRatio":1,"width":21,"x":157,"y":257},"blue_str_penta_4":{"height":14,"pixelRatio":1,"width":25,"x":380,"y":101},"blue_str_penta_5":{"height":14,"pixelRatio":1,"width":29,"x":213,"y":134},"blue_str_penta_6":{"height":14,"pixelRatio":1,"width":33,"x":292,"y":38},"blue_str_penta_yellow_1":{"height":14,"pixelRatio":1,"width":12,"x":311,"y":134},"blue_str_penta_yellow_2":{"height":14,"pixelRatio":1,"width":16,"x":416,"y":195},"blue_str_penta_yellow_3":{"height":14,"pixelRatio":1,"width":21,"x":157,"y":257},"blue_str_penta_yellow_4":{"height":14,"pixelRatio":1,"width":25,"x":380,"y":101},"blue_str_penta_yellow_5":{"height":14,"pixelRatio":1,"width":29,"x":213,"y":134},"blue_str_penta_yellow_6":{"height":14,"pixelRatio":1,"width":33,"x":292,"y":38},"blue_yellow_1":{"height":14,"pixelRatio":1,"width":14,"x":76,"y":312},"blue_yellow_2":{"height":14,"pixelRatio":1,"width":18,"x":105,"y":353},"blue_yellow_3":{"height":14,"pixelRatio":1,"width":23,"x":27,"y":474},"blue_yellow_4":{"height":14,"pixelRatio":1,"width":28,"x":75,"y":353},"blue_yellow_5":{"height":14,"pixelRatio":1,"width":32,"x":437,"y":35},"blue_yellow_6":{"height":14,"pixelRatio":1,"width":37,"x":52,"y":120},"boston-t":{"height":17,"pixelRatio":1,"width":20,"x":202,"y":479},"brn_green_1":{"height":14,"pixelRatio":1,"width":14,"x":460,"y":250},"brn_green_2":{"height":14,"pixelRatio":1,"width":18,"x":370,"y":373},"brn_green_3":{"height":14,"pixelRatio":1,"width":23,"x":264,"y":213},"brn_green_4":{"height":14,"pixelRatio":1,"width":28,"x":211,"y":287},"brn_green_5":{"height":14,"pixelRatio":1,"width":32,"x":81,"y":270},"brn_green_6":{"height":14,"pixelRatio":1,"width":37,"x":43,"y":184},"bus-11":{"height":17,"pixelRatio":1,"width":17,"x":288,"y":375},"bus-15":{"height":21,"pixelRatio":1,"width":21,"x":264,"y":167},"cafe-11":{"height":19,"pixelRatio":1,"width":19,"x":434,"y":115},"cafe-15":{"height":23,"pixelRatio":1,"width":23,"x":107,"y":204},"campsite-11":{"height":19,"pixelRatio":1,"width":19,"x":455,"y":115},"campsite-15":{"height":23,"pixelRatio":1,"width":23,"x":107,"y":229},"can_leaf_1":{"height":14,"pixelRatio":1,"width":13,"x":358,"y":467},"can_leaf_2":{"height":14,"pixelRatio":1,"width":18,"x":369,"y":389},"can_leaf_3":{"height":14,"pixelRatio":1,"width":22,"x":264,"y":376},"can_leaf_4":{"height":14,"pixelRatio":1,"width":27,"x":215,"y":102},"can_leaf_5":{"height":14,"pixelRatio":1,"width":31,"x":180,"y":134},"can_leaf_6":{"height":14,"pixelRatio":1,"width":36,"x":181,"y":38},"car-11":{"height":19,"pixelRatio":1,"width":19,"x":260,"y":229},"car-15":{"height":23,"pixelRatio":1,"width":23,"x":81,"y":286},"castle-11":{"height":19,"pixelRatio":1,"width":19,"x":289,"y":212},"castle-15":{"height":23,"pixelRatio":1,"width":23,"x":41,"y":328},"cemetery-11":{"height":19,"pixelRatio":1,"width":19,"x":262,"y":250},"cemetery-15":{"height":23,"pixelRatio":1,"width":23,"x":66,"y":328},"chi_blue_1":{"height":14,"pixelRatio":1,"width":13,"x":389,"y":463},"chi_blue_2":{"height":14,"pixelRatio":1,"width":17,"x":462,"y":285},"chi_blue_3":{"height":14,"pixelRatio":1,"width":21,"x":262,"y":450},"chi_blue_4":{"height":14,"pixelRatio":1,"width":26,"x":380,"y":117},"chi_blue_5":{"height":14,"pixelRatio":1,"width":30,"x":182,"y":232},"chi_blue_6":{"height":14,"pixelRatio":1,"width":34,"x":217,"y":54},"chi_green_1":{"height":14,"pixelRatio":1,"width":13,"x":389,"y":479},"chi_green_2":{"height":14,"pixelRatio":1,"width":17,"x":462,"y":301},"chi_green_3":{"height":14,"pixelRatio":1,"width":21,"x":304,"y":450},"chi_green_4":{"height":14,"pixelRatio":1,"width":26,"x":406,"y":75},"chi_green_5":{"height":14,"pixelRatio":1,"width":30,"x":232,"y":167},"chi_green_6":{"height":14,"pixelRatio":1,"width":34,"x":256,"y":38},"chongqing-rail-transit":{"height":17,"pixelRatio":1,"width":30,"x":109,"y":23},"cinema-11":{"height":19,"pixelRatio":1,"width":19,"x":262,"y":271},"cinema-15":{"height":23,"pixelRatio":1,"width":23,"x":46,"y":369},"clothing-store-11":{"height":19,"pixelRatio":1,"width":19,"x":283,"y":249},"clothing-store-15":{"height":23,"pixelRatio":1,"width":23,"x":27,"y":399},"college-11":{"height":19,"pixelRatio":1,"width":19,"x":283,"y":270},"college-15":{"height":23,"pixelRatio":1,"width":23,"x":27,"y":424},"de-s-bahn":{"height":17,"pixelRatio":1,"width":17,"x":415,"y":176},"de-s-bahn.de-u-bahn":{"height":33,"pixelRatio":1,"width":17,"x":2,"y":374},"de-u-bahn":{"height":17,"pixelRatio":1,"width":17,"x":350,"y":388},"delhi-metro":{"height":17,"pixelRatio":1,"width":20,"x":224,"y":479},"dentist-11":{"height":19,"pixelRatio":1,"width":19,"x":263,"y":292},"dentist-15":{"height":23,"pixelRatio":1,"width":23,"x":27,"y":449},"doctor-11":{"height":19,"pixelRatio":1,"width":19,"x":263,"y":313},"doctor-15":{"height":23,"pixelRatio":1,"width":23,"x":52,"y":394},"dog-park-11":{"height":19,"pixelRatio":1,"width":19,"x":284,"y":291},"dog-park-15":{"height":23,"pixelRatio":1,"width":23,"x":52,"y":419},"dom_1":{"height":14,"pixelRatio":1,"width":10,"x":135,"y":106},"dom_2":{"height":14,"pixelRatio":1,"width":14,"x":370,"y":357},"dom_3":{"height":14,"pixelRatio":1,"width":17,"x":461,"y":336},"dom_4":{"height":14,"pixelRatio":1,"width":21,"x":352,"y":146},"dom_5":{"height":14,"pixelRatio":1,"width":24,"x":461,"y":99},"dom_6":{"height":14,"pixelRatio":1,"width":28,"x":212,"y":303},"dot-10":{"height":10,"pixelRatio":1,"width":10,"x":177,"y":486},"dot-11":{"height":11,"pixelRatio":1,"width":11,"x":123,"y":141},"dot-9":{"height":9,"pixelRatio":1,"width":9,"x":487,"y":99},"drinking-water-11":{"height":19,"pixelRatio":1,"width":19,"x":284,"y":312},"drinking-water-15":{"height":23,"pixelRatio":1,"width":23,"x":52,"y":444},"embassy-11":{"height":19,"pixelRatio":1,"width":19,"x":264,"y":334},"embassy-15":{"height":23,"pixelRatio":1,"width":23,"x":52,"y":469},"entrance":{"height":15,"pixelRatio":1,"width":15,"x":459,"y":152},"fast-food-11":{"height":19,"pixelRatio":1,"width":19,"x":264,"y":355},"fast-food-15":{"height":23,"pixelRatio":1,"width":23,"x":71,"y":369},"ferry-11":{"height":17,"pixelRatio":1,"width":17,"x":351,"y":407},"ferry-15":{"height":21,"pixelRatio":1,"width":21,"x":264,"y":190},"fire-station-11":{"height":19,"pixelRatio":1,"width":19,"x":285,"y":333},"fire-station-15":{"height":23,"pixelRatio":1,"width":23,"x":77,"y":394},"fuel-11":{"height":19,"pixelRatio":1,"width":19,"x":285,"y":354},"fuel-15":{"height":23,"pixelRatio":1,"width":23,"x":77,"y":419},"garden-11":{"height":19,"pixelRatio":1,"width":19,"x":263,"y":392},"garden-15":{"height":23,"pixelRatio":1,"width":23,"x":77,"y":444},"gb-national-rail":{"height":15,"pixelRatio":1,"width":17,"x":147,"y":311},"gb-national-rail.london-dlr":{"height":19,"pixelRatio":1,"width":39,"x":2,"y":152},"gb-national-rail.london-dlr.london-overground.london-tfl-rail.london-underground":{"height":34,"pixelRatio":1,"width":60,"x":2,"y":2},"gb-national-rail.london-dlr.london-overground.london-underground":{"height":19,"pixelRatio":1,"width":75,"x":64,"y":2},"gb-national-rail.london-dlr.london-underground":{"height":19,"pixelRatio":1,"width":57,"x":2,"y":38},"gb-national-rail.london-overground":{"height":19,"pixelRatio":1,"width":39,"x":2,"y":173},"gb-national-rail.london-overground.london-tfl-rail.london-underground":{"height":18,"pixelRatio":1,"width":75,"x":141,"y":2},"gb-national-rail.london-overground.london-underground":{"height":19,"pixelRatio":1,"width":57,"x":2,"y":59},"gb-national-rail.london-tfl-rail":{"height":17,"pixelRatio":1,"width":37,"x":2,"y":317},"gb-national-rail.london-tfl-rail.london-overground":{"height":18,"pixelRatio":1,"width":56,"x":218,"y":2},"gb-national-rail.london-tfl-rail.london-underground":{"height":18,"pixelRatio":1,"width":56,"x":2,"y":80},"gb-national-rail.london-underground":{"height":19,"pixelRatio":1,"width":39,"x":2,"y":194},"golf-11":{"height":19,"pixelRatio":1,"width":19,"x":262,"y":429},"golf-15":{"height":23,"pixelRatio":1,"width":23,"x":77,"y":469},"green_1":{"height":14,"pixelRatio":1,"width":14,"x":428,"y":443},"green_2":{"height":14,"pixelRatio":1,"width":18,"x":390,"y":367},"green_3":{"height":14,"pixelRatio":1,"width":23,"x":281,"y":233},"green_4":{"height":14,"pixelRatio":1,"width":28,"x":212,"y":319},"green_5":{"height":14,"pixelRatio":1,"width":32,"x":42,"y":312},"green_6":{"height":14,"pixelRatio":1,"width":37,"x":43,"y":200},"green_circle_1":{"height":14,"pixelRatio":1,"width":14,"x":444,"y":448},"green_circle_2":{"height":14,"pixelRatio":1,"width":19,"x":400,"y":160},"green_circle_3":{"height":14,"pixelRatio":1,"width":24,"x":408,"y":107},"green_circle_4":{"height":14,"pixelRatio":1,"width":28,"x":212,"y":335},"green_circle_5":{"height":14,"pixelRatio":1,"width":33,"x":288,"y":54},"green_circle_6":{"height":14,"pixelRatio":1,"width":38,"x":60,"y":104},"green_half_circle_1":{"height":14,"pixelRatio":1,"width":12,"x":484,"y":429},"green_half_circle_2":{"height":14,"pixelRatio":1,"width":16,"x":480,"y":317},"green_half_circle_3":{"height":14,"pixelRatio":1,"width":20,"x":306,"y":395},"green_half_circle_4":{"height":14,"pixelRatio":1,"width":24,"x":408,"y":123},"green_half_circle_5":{"height":14,"pixelRatio":1,"width":28,"x":213,"y":351},"green_half_circle_6":{"height":14,"pixelRatio":1,"width":32,"x":142,"y":86},"green_octagon_1":{"height":14,"pixelRatio":1,"width":14,"x":246,"y":465},"green_octagon_2":{"height":14,"pixelRatio":1,"width":18,"x":410,"y":361},"green_octagon_3":{"height":14,"pixelRatio":1,"width":23,"x":263,"y":413},"green_octagon_4":{"height":14,"pixelRatio":1,"width":28,"x":213,"y":367},"green_octagon_5":{"height":14,"pixelRatio":1,"width":32,"x":176,"y":86},"green_octagon_6":{"height":14,"pixelRatio":1,"width":37,"x":43,"y":216},"green_rnd_shield_1":{"height":14,"pixelRatio":1,"width":11,"x":421,"y":139},"green_rnd_shield_2":{"height":14,"pixelRatio":1,"width":15,"x":459,"y":169},"green_rnd_shield_3":{"height":14,"pixelRatio":1,"width":19,"x":416,"y":232},"green_rnd_shield_4":{"height":14,"pixelRatio":1,"width":23,"x":325,"y":130},"green_rnd_shield_5":{"height":14,"pixelRatio":1,"width":27,"x":215,"y":118},"green_rnd_shield_6":{"height":14,"pixelRatio":1,"width":31,"x":244,"y":135},"green_rnd_shield_yellow_1":{"height":14,"pixelRatio":1,"width":11,"x":421,"y":139},"green_rnd_shield_yellow_2":{"height":14,"pixelRatio":1,"width":15,"x":459,"y":169},"green_rnd_shield_yellow_3":{"height":14,"pixelRatio":1,"width":19,"x":416,"y":232},"green_rnd_shield_yellow_4":{"height":14,"pixelRatio":1,"width":23,"x":325,"y":130},"green_rnd_shield_yellow_5":{"height":14,"pixelRatio":1,"width":27,"x":215,"y":118},"green_rnd_shield_yellow_6":{"height":14,"pixelRatio":1,"width":31,"x":244,"y":135},"green_sixtangle_1":{"height":14,"pixelRatio":1,"width":14,"x":246,"y":481},"green_sixtangle_2":{"height":14,"pixelRatio":1,"width":18,"x":430,"y":363},"green_sixtangle_3":{"height":14,"pixelRatio":1,"width":23,"x":350,"y":130},"green_sixtangle_4":{"height":14,"pixelRatio":1,"width":28,"x":202,"y":415},"green_sixtangle_5":{"height":14,"pixelRatio":1,"width":32,"x":210,"y":86},"green_sixtangle_6":{"height":14,"pixelRatio":1,"width":37,"x":43,"y":232},"green_square90_1":{"height":14,"pixelRatio":1,"width":14,"x":262,"y":466},"green_square90_2":{"height":14,"pixelRatio":1,"width":18,"x":410,"y":377},"green_square90_3":{"height":14,"pixelRatio":1,"width":23,"x":375,"y":133},"green_square90_4":{"height":14,"pixelRatio":1,"width":28,"x":202,"y":431},"green_square90_5":{"height":14,"pixelRatio":1,"width":32,"x":244,"y":87},"green_square90_6":{"height":14,"pixelRatio":1,"width":37,"x":141,"y":22},"green_str_penta_1":{"height":14,"pixelRatio":1,"width":12,"x":404,"y":463},"green_str_penta_2":{"height":14,"pixelRatio":1,"width":16,"x":480,"y":333},"green_str_penta_3":{"height":14,"pixelRatio":1,"width":21,"x":437,"y":219},"green_str_penta_4":{"height":14,"pixelRatio":1,"width":25,"x":463,"y":67},"green_str_penta_5":{"height":14,"pixelRatio":1,"width":29,"x":180,"y":248},"green_str_penta_6":{"height":14,"pixelRatio":1,"width":33,"x":253,"y":71},"green_yellow_1":{"height":14,"pixelRatio":1,"width":14,"x":428,"y":443},"green_yellow_2":{"height":14,"pixelRatio":1,"width":18,"x":390,"y":367},"green_yellow_3":{"height":14,"pixelRatio":1,"width":23,"x":281,"y":233},"green_yellow_4":{"height":14,"pixelRatio":1,"width":28,"x":212,"y":319},"green_yellow_5":{"height":14,"pixelRatio":1,"width":32,"x":42,"y":312},"green_yellow_6":{"height":14,"pixelRatio":1,"width":37,"x":43,"y":200},"grocery-11":{"height":19,"pixelRatio":1,"width":19,"x":283,"y":429},"grocery-15":{"height":23,"pixelRatio":1,"width":23,"x":91,"y":328},"gua_white_1":{"height":14,"pixelRatio":1,"width":10,"x":136,"y":150},"gua_white_2":{"height":14,"pixelRatio":1,"width":14,"x":262,"y":482},"gua_white_3":{"height":14,"pixelRatio":1,"width":18,"x":390,"y":383},"gua_white_4":{"height":14,"pixelRatio":1,"width":21,"x":437,"y":235},"gua_white_5":{"height":14,"pixelRatio":1,"width":25,"x":434,"y":83},"gua_white_6":{"height":14,"pixelRatio":1,"width":29,"x":180,"y":264},"hairdresser-11":{"height":19,"pixelRatio":1,"width":19,"x":304,"y":429},"hairdresser-15":{"height":23,"pixelRatio":1,"width":23,"x":106,"y":286},"harbor-11":{"height":19,"pixelRatio":1,"width":19,"x":310,"y":150},"harbor-15":{"height":23,"pixelRatio":1,"width":23,"x":96,"y":369},"heliport-11":{"height":17,"pixelRatio":1,"width":17,"x":462,"y":266},"heliport-15":{"height":21,"pixelRatio":1,"width":21,"x":287,"y":166},"hkg_yellow_1":{"height":14,"pixelRatio":1,"width":13,"x":470,"y":413},"hkg_yellow_2":{"height":14,"pixelRatio":1,"width":17,"x":370,"y":422},"hkg_yellow_3":{"height":14,"pixelRatio":1,"width":21,"x":437,"y":251},"hkg_yellow_4":{"height":14,"pixelRatio":1,"width":26,"x":437,"y":51},"hkg_yellow_5":{"height":14,"pixelRatio":1,"width":30,"x":232,"y":183},"hkg_yellow_6":{"height":14,"pixelRatio":1,"width":35,"x":180,"y":54},"hong-kong-mtr":{"height":17,"pixelRatio":1,"width":20,"x":476,"y":115},"hospital-11":{"height":19,"pixelRatio":1,"width":19,"x":310,"y":171},"hospital-15":{"height":23,"pixelRatio":1,"width":23,"x":102,"y":394},"ice-cream-11":{"height":19,"pixelRatio":1,"width":19,"x":310,"y":192},"ice-cream-15":{"height":23,"pixelRatio":1,"width":23,"x":102,"y":419},"information-11":{"height":19,"pixelRatio":1,"width":19,"x":310,"y":213},"information-15":{"height":23,"pixelRatio":1,"width":23,"x":102,"y":444},"kiev-metro":{"height":17,"pixelRatio":1,"width":20,"x":476,"y":134},"kor_sixtangle_1":{"height":14,"pixelRatio":1,"width":19,"x":395,"y":239},"kor_sixtangle_2":{"height":14,"pixelRatio":1,"width":26,"x":465,"y":51},"kor_sixtangle_3":{"height":14,"pixelRatio":1,"width":33,"x":288,"y":70},"kor_sixtangle_4":{"height":14,"pixelRatio":1,"width":39,"x":60,"y":88},"kor_sixtangle_5":{"height":14,"pixelRatio":1,"width":46,"x":2,"y":136},"kor_sixtangle_6":{"height":14,"pixelRatio":1,"width":52,"x":334,"y":2},"laundry-11":{"height":19,"pixelRatio":1,"width":19,"x":331,"y":146},"laundry-15":{"height":23,"pixelRatio":1,"width":23,"x":102,"y":469},"library-11":{"height":19,"pixelRatio":1,"width":19,"x":331,"y":167},"library-15":{"height":23,"pixelRatio":1,"width":23,"x":116,"y":328},"lodging-11":{"height":19,"pixelRatio":1,"width":19,"x":352,"y":162},"lodging-15":{"height":23,"pixelRatio":1,"width":23,"x":121,"y":369},"london-dlr":{"height":19,"pixelRatio":1,"width":19,"x":331,"y":188},"london-dlr.london-tfl-rail":{"height":18,"pixelRatio":1,"width":38,"x":2,"y":257},"london-dlr.london-tfl-rail.london-underground":{"height":18,"pixelRatio":1,"width":56,"x":276,"y":2},"london-dlr.london-underground":{"height":19,"pixelRatio":1,"width":39,"x":2,"y":215},"london-overground":{"height":19,"pixelRatio":1,"width":19,"x":352,"y":183},"london-overground.london-tfl-rail":{"height":18,"pixelRatio":1,"width":38,"x":2,"y":277},"london-overground.london-tfl-rail.london-underground":{"height":18,"pixelRatio":1,"width":56,"x":2,"y":100},"london-overground.london-underground":{"height":19,"pixelRatio":1,"width":39,"x":2,"y":236},"london-tfl-rail":{"height":17,"pixelRatio":1,"width":20,"x":284,"y":394},"london-tfl-rail.london-underground":{"height":18,"pixelRatio":1,"width":38,"x":2,"y":297},"london-underground":{"height":19,"pixelRatio":1,"width":19,"x":331,"y":209},"madrid-metro":{"height":17,"pixelRatio":1,"width":20,"x":373,"y":207},"marker-11":{"height":19,"pixelRatio":1,"width":19,"x":352,"y":204},"marker-15":{"height":23,"pixelRatio":1,"width":23,"x":127,"y":394},"marsh-16":{"height":16,"pixelRatio":1,"width":16,"x":308,"y":411},"mexico-city-metro":{"height":17,"pixelRatio":1,"width":20,"x":373,"y":226},"milan-metro":{"height":17,"pixelRatio":1,"width":20,"x":304,"y":271},"monument-11":{"height":19,"pixelRatio":1,"width":19,"x":373,"y":165},"monument-15":{"height":23,"pixelRatio":1,"width":23,"x":127,"y":419},"moscow-metro":{"height":15,"pixelRatio":1,"width":17,"x":370,"y":405},"mountain-11":{"height":19,"pixelRatio":1,"width":19,"x":373,"y":186},"mountain-15":{"height":23,"pixelRatio":1,"width":23,"x":127,"y":444},"museum-11":{"height":19,"pixelRatio":1,"width":19,"x":331,"y":230},"museum-15":{"height":23,"pixelRatio":1,"width":23,"x":127,"y":469},"music-11":{"height":19,"pixelRatio":1,"width":19,"x":352,"y":225},"music-15":{"height":23,"pixelRatio":1,"width":23,"x":141,"y":328},"new-york-subway":{"height":17,"pixelRatio":1,"width":20,"x":325,"y":251},"oneway-spaced-large":{"height":6,"pixelRatio":1,"width":14,"x":132,"y":241},"oneway-spaced-small":{"height":5,"pixelRatio":1,"width":11,"x":189,"y":486},"oneway-spaced-white-large":{"height":6,"pixelRatio":1,"width":14,"x":192,"y":375},"oneway-spaced-white-small":{"height":5,"pixelRatio":1,"width":11,"x":2,"y":484},"orange_1":{"height":14,"pixelRatio":1,"width":14,"x":278,"y":466},"orange_2":{"height":14,"pixelRatio":1,"width":18,"x":389,"y":399},"orange_3":{"height":14,"pixelRatio":1,"width":23,"x":375,"y":149},"orange_4":{"height":14,"pixelRatio":1,"width":28,"x":202,"y":447},"orange_5":{"height":14,"pixelRatio":1,"width":32,"x":334,"y":34},"orange_6":{"height":14,"pixelRatio":1,"width":37,"x":180,"y":22},"osaka-subway":{"height":17,"pixelRatio":1,"width":20,"x":326,"y":312},"oslo-metro":{"height":17,"pixelRatio":1,"width":20,"x":328,"y":394},"pak_green_half_circle_1":{"height":14,"pixelRatio":1,"width":14,"x":278,"y":482},"pak_green_half_circle_2":{"height":14,"pixelRatio":1,"width":18,"x":430,"y":379},"pak_green_half_circle_3":{"height":14,"pixelRatio":1,"width":23,"x":306,"y":234},"pak_green_half_circle_4":{"height":14,"pixelRatio":1,"width":28,"x":202,"y":463},"pak_green_half_circle_5":{"height":14,"pixelRatio":1,"width":32,"x":368,"y":34},"pak_green_half_circle_6":{"height":14,"pixelRatio":1,"width":37,"x":219,"y":22},"paris-metro":{"height":17,"pixelRatio":1,"width":17,"x":346,"y":429},"paris-metro.paris-rer":{"height":17,"pixelRatio":1,"width":37,"x":2,"y":336},"paris-rer":{"height":17,"pixelRatio":1,"width":17,"x":347,"y":448},"paris-rer.paris-transilien":{"height":17,"pixelRatio":1,"width":35,"x":2,"y":355},"paris-transilien":{"height":17,"pixelRatio":1,"width":17,"x":368,"y":262},"park-11":{"height":19,"pixelRatio":1,"width":19,"x":304,"y":250},"park-15":{"height":23,"pixelRatio":1,"width":23,"x":152,"y":393},"pharmacy-11":{"height":19,"pixelRatio":1,"width":19,"x":305,"y":290},"pharmacy-15":{"height":23,"pixelRatio":1,"width":23,"x":152,"y":418},"philadelphia-septa":{"height":17,"pixelRatio":1,"width":20,"x":476,"y":153},"picnic-site-11":{"height":19,"pixelRatio":1,"width":19,"x":305,"y":311},"picnic-site-15":{"height":23,"pixelRatio":1,"width":23,"x":152,"y":443},"place-of-worship-11":{"height":19,"pixelRatio":1,"width":19,"x":306,"y":332},"place-of-worship-15":{"height":23,"pixelRatio":1,"width":23,"x":152,"y":468},"playground-11":{"height":19,"pixelRatio":1,"width":19,"x":306,"y":353},"playground-15":{"height":23,"pixelRatio":1,"width":23,"x":131,"y":286},"police-11":{"height":19,"pixelRatio":1,"width":19,"x":307,"y":374},"police-15":{"height":23,"pixelRatio":1,"width":23,"x":156,"y":286},"post-11":{"height":19,"pixelRatio":1,"width":19,"x":326,"y":270},"post-15":{"height":23,"pixelRatio":1,"width":23,"x":166,"y":311},"prison-11":{"height":19,"pixelRatio":1,"width":19,"x":326,"y":291},"prison-15":{"height":23,"pixelRatio":1,"width":23,"x":166,"y":336},"qe_green_1":{"height":14,"pixelRatio":1,"width":14,"x":294,"y":466},"qe_green_2":{"height":14,"pixelRatio":1,"width":18,"x":410,"y":393},"qe_green_3":{"height":14,"pixelRatio":1,"width":23,"x":326,"y":413},"qe_green_4":{"height":14,"pixelRatio":1,"width":28,"x":233,"y":385},"qe_green_5":{"height":14,"pixelRatio":1,"width":32,"x":41,"y":353},"qe_green_6":{"height":14,"pixelRatio":1,"width":37,"x":258,"y":22},"rail":{"height":17,"pixelRatio":1,"width":17,"x":369,"y":319},"rail-light":{"height":17,"pixelRatio":1,"width":17,"x":368,"y":281},"rail-metro":{"height":17,"pixelRatio":1,"width":17,"x":369,"y":300},"red_1":{"height":14,"pixelRatio":1,"width":14,"x":294,"y":482},"red_2":{"height":14,"pixelRatio":1,"width":18,"x":430,"y":395},"red_3":{"height":14,"pixelRatio":1,"width":23,"x":434,"y":152},"red_4":{"height":14,"pixelRatio":1,"width":28,"x":233,"y":401},"red_5":{"height":14,"pixelRatio":1,"width":32,"x":288,"y":86},"red_6":{"height":14,"pixelRatio":1,"width":37,"x":334,"y":18},"red_penta_1":{"height":14,"pixelRatio":1,"width":14,"x":310,"y":466},"red_penta_2":{"height":14,"pixelRatio":1,"width":18,"x":450,"y":368},"red_penta_3":{"height":14,"pixelRatio":1,"width":23,"x":434,"y":168},"red_penta_4":{"height":14,"pixelRatio":1,"width":28,"x":232,"y":417},"red_penta_5":{"height":14,"pixelRatio":1,"width":32,"x":288,"y":102},"red_penta_6":{"height":14,"pixelRatio":1,"width":37,"x":373,"y":18},"red_rnd_shield_1":{"height":14,"pixelRatio":1,"width":11,"x":421,"y":155},"red_rnd_shield_2":{"height":14,"pixelRatio":1,"width":15,"x":459,"y":185},"red_rnd_shield_3":{"height":14,"pixelRatio":1,"width":19,"x":352,"y":246},"red_rnd_shield_4":{"height":14,"pixelRatio":1,"width":23,"x":434,"y":184},"red_rnd_shield_5":{"height":14,"pixelRatio":1,"width":27,"x":353,"y":66},"red_rnd_shield_6":{"height":14,"pixelRatio":1,"width":31,"x":278,"y":134},"red_rnd_triangle_1":{"height":14,"pixelRatio":1,"width":12,"x":404,"y":479},"red_rnd_triangle_2":{"height":14,"pixelRatio":1,"width":16,"x":480,"y":349},"red_rnd_triangle_3":{"height":14,"pixelRatio":1,"width":20,"x":476,"y":248},"red_rnd_triangle_4":{"height":14,"pixelRatio":1,"width":24,"x":434,"y":136},"red_rnd_triangle_5":{"height":14,"pixelRatio":1,"width":28,"x":232,"y":433},"red_rnd_triangle_6":{"height":14,"pixelRatio":1,"width":33,"x":101,"y":90},"red_sixtangle_1":{"height":14,"pixelRatio":1,"width":14,"x":310,"y":482},"red_sixtangle_2":{"height":14,"pixelRatio":1,"width":18,"x":450,"y":384},"red_sixtangle_3":{"height":14,"pixelRatio":1,"width":23,"x":437,"y":267},"red_sixtangle_4":{"height":14,"pixelRatio":1,"width":28,"x":232,"y":449},"red_sixtangle_5":{"height":14,"pixelRatio":1,"width":32,"x":147,"y":102},"red_sixtangle_6":{"height":14,"pixelRatio":1,"width":37,"x":43,"y":248},"religious-christian-11":{"height":19,"pixelRatio":1,"width":19,"x":327,"y":331},"religious-christian-15":{"height":23,"pixelRatio":1,"width":23,"x":167,"y":361},"religious-jewish-11":{"height":19,"pixelRatio":1,"width":19,"x":327,"y":352},"religious-jewish-15":{"height":23,"pixelRatio":1,"width":23,"x":177,"y":386},"religious-muslim-11":{"height":19,"pixelRatio":1,"width":19,"x":328,"y":373},"religious-muslim-15":{"height":23,"pixelRatio":1,"width":23,"x":177,"y":411},"restaurant-11":{"height":19,"pixelRatio":1,"width":19,"x":325,"y":429},"restaurant-15":{"height":23,"pixelRatio":1,"width":23,"x":177,"y":436},"rocket-11":{"height":17,"pixelRatio":1,"width":17,"x":369,"y":338},"rocket-15":{"height":21,"pixelRatio":1,"width":21,"x":287,"y":189},"rom_red_shield_1":{"height":14,"pixelRatio":1,"width":14,"x":326,"y":466},"rom_red_shield_2":{"height":14,"pixelRatio":1,"width":18,"x":450,"y":400},"rom_red_shield_3":{"height":14,"pixelRatio":1,"width":23,"x":387,"y":271},"rom_red_shield_4":{"height":14,"pixelRatio":1,"width":28,"x":327,"y":50},"rom_red_shield_5":{"height":14,"pixelRatio":1,"width":32,"x":181,"y":102},"rom_red_shield_6":{"height":14,"pixelRatio":1,"width":37,"x":42,"y":264},"san-francisco-bart":{"height":17,"pixelRatio":1,"width":20,"x":476,"y":172},"school-11":{"height":19,"pixelRatio":1,"width":19,"x":400,"y":139},"school-15":{"height":23,"pixelRatio":1,"width":23,"x":177,"y":461},"shop-11":{"height":19,"pixelRatio":1,"width":19,"x":394,"y":176},"shop-15":{"height":23,"pixelRatio":1,"width":23,"x":132,"y":166},"singapore-mrt":{"height":17,"pixelRatio":1,"width":20,"x":476,"y":191},"stadium-11":{"height":19,"pixelRatio":1,"width":19,"x":395,"y":197},"stadium-15":{"height":23,"pixelRatio":1,"width":23,"x":157,"y":166},"stockholm-metro":{"height":17,"pixelRatio":1,"width":20,"x":437,"y":200},"suitcase-11":{"height":19,"pixelRatio":1,"width":19,"x":395,"y":218},"suitcase-15":{"height":23,"pixelRatio":1,"width":23,"x":132,"y":191},"svk_blue_1":{"height":14,"pixelRatio":1,"width":18,"x":389,"y":415},"svk_blue_2":{"height":14,"pixelRatio":1,"width":23,"x":412,"y":281},"svk_blue_3":{"height":14,"pixelRatio":1,"width":29,"x":202,"y":383},"svk_blue_4":{"height":14,"pixelRatio":1,"width":32,"x":244,"y":103},"svk_blue_5":{"height":14,"pixelRatio":1,"width":37,"x":42,"y":280},"svk_blue_6":{"height":14,"pixelRatio":1,"width":47,"x":388,"y":2},"swimming-11":{"height":19,"pixelRatio":1,"width":19,"x":416,"y":211},"swimming-15":{"height":23,"pixelRatio":1,"width":23,"x":157,"y":191},"taipei-metro":{"height":17,"pixelRatio":1,"width":20,"x":476,"y":210},"theatre-11":{"height":19,"pixelRatio":1,"width":19,"x":347,"y":262},"theatre-15":{"height":23,"pixelRatio":1,"width":23,"x":182,"y":166},"toilet-11":{"height":19,"pixelRatio":1,"width":19,"x":347,"y":283},"toilet-15":{"height":23,"pixelRatio":1,"width":23,"x":132,"y":216},"tokyo-metro":{"height":17,"pixelRatio":1,"width":20,"x":476,"y":229},"town-hall-11":{"height":19,"pixelRatio":1,"width":19,"x":348,"y":304},"town-hall-15":{"height":23,"pixelRatio":1,"width":23,"x":157,"y":216},"us_blue_red_rnd_shield_1":{"height":14,"pixelRatio":1,"width":14,"x":326,"y":482},"us_blue_red_rnd_shield_2":{"height":14,"pixelRatio":1,"width":18,"x":409,"y":409},"us_blue_red_rnd_shield_3":{"height":14,"pixelRatio":1,"width":23,"x":437,"y":283},"us_blue_red_rnd_shield_4":{"height":14,"pixelRatio":1,"width":28,"x":357,"y":50},"us_blue_red_rnd_shield_5":{"height":14,"pixelRatio":1,"width":33,"x":100,"y":106},"us_blue_red_rnd_shield_6":{"height":15,"pixelRatio":1,"width":43,"x":437,"y":2},"us_blue_red_shield_1":{"height":14,"pixelRatio":1,"width":13,"x":469,"y":429},"us_blue_red_shield_2":{"height":14,"pixelRatio":1,"width":17,"x":470,"y":381},"us_blue_red_shield_3":{"height":14,"pixelRatio":1,"width":21,"x":413,"y":313},"us_blue_red_shield_4":{"height":14,"pixelRatio":1,"width":26,"x":435,"y":67},"us_blue_red_shield_5":{"height":14,"pixelRatio":1,"width":30,"x":232,"y":199},"us_blue_red_shield_6":{"height":14,"pixelRatio":1,"width":34,"x":217,"y":70},"veterinary-11":{"height":19,"pixelRatio":1,"width":19,"x":348,"y":325},"veterinary-15":{"height":23,"pixelRatio":1,"width":23,"x":207,"y":166},"vienna-u-bahn":{"height":15,"pixelRatio":1,"width":15,"x":459,"y":201},"volcano-11":{"height":19,"pixelRatio":1,"width":19,"x":348,"y":346},"volcano-15":{"height":23,"pixelRatio":1,"width":23,"x":182,"y":191},"washington-metro":{"height":17,"pixelRatio":1,"width":17,"x":461,"y":317},"white_1":{"height":14,"pixelRatio":1,"width":14,"x":342,"y":467},"white_2":{"height":14,"pixelRatio":1,"width":18,"x":429,"y":411},"white_3":{"height":14,"pixelRatio":1,"width":23,"x":388,"y":303},"white_4":{"height":14,"pixelRatio":1,"width":27,"x":323,"y":82},"white_5":{"height":14,"pixelRatio":1,"width":32,"x":147,"y":118},"white_6":{"height":14,"pixelRatio":1,"width":37,"x":42,"y":296},"white_blue_1":{"height":14,"pixelRatio":1,"width":14,"x":342,"y":467},"white_blue_2":{"height":14,"pixelRatio":1,"width":18,"x":429,"y":411},"white_blue_3":{"height":14,"pixelRatio":1,"width":23,"x":388,"y":303},"white_blue_4":{"height":14,"pixelRatio":1,"width":27,"x":323,"y":82},"white_blue_5":{"height":14,"pixelRatio":1,"width":32,"x":147,"y":118},"white_blue_6":{"height":14,"pixelRatio":1,"width":37,"x":42,"y":296},"white_circle_1":{"height":14,"pixelRatio":1,"width":15,"x":481,"y":264},"white_circle_2":{"height":14,"pixelRatio":1,"width":20,"x":373,"y":245},"white_circle_3":{"height":14,"pixelRatio":1,"width":25,"x":461,"y":83},"white_circle_4":{"height":14,"pixelRatio":1,"width":30,"x":148,"y":241},"white_circle_5":{"height":14,"pixelRatio":1,"width":35,"x":219,"y":38},"white_circle_6":{"height":14,"pixelRatio":1,"width":40,"x":61,"y":72},"white_green_1":{"height":14,"pixelRatio":1,"width":14,"x":342,"y":467},"white_green_2":{"height":14,"pixelRatio":1,"width":18,"x":429,"y":411},"white_green_3":{"height":14,"pixelRatio":1,"width":23,"x":388,"y":303},"white_green_4":{"height":14,"pixelRatio":1,"width":27,"x":323,"y":82},"white_green_5":{"height":14,"pixelRatio":1,"width":32,"x":147,"y":118},"white_green_6":{"height":14,"pixelRatio":1,"width":37,"x":42,"y":296},"white_mxx_shield_1":{"height":15,"pixelRatio":1,"width":14,"x":482,"y":2},"white_mxx_shield_2":{"height":15,"pixelRatio":1,"width":19,"x":416,"y":248},"white_mxx_shield_3":{"height":15,"pixelRatio":1,"width":23,"x":92,"y":311},"white_mxx_shield_4":{"height":15,"pixelRatio":1,"width":28,"x":117,"y":311},"white_mxx_shield_5":{"height":15,"pixelRatio":1,"width":33,"x":253,"y":54},"white_mxx_shield_6":{"height":15,"pixelRatio":1,"width":43,"x":64,"y":23},"white_old_shield_1":{"height":14,"pixelRatio":1,"width":13,"x":475,"y":445},"white_old_shield_2":{"height":14,"pixelRatio":1,"width":18,"x":449,"y":416},"white_old_shield_3":{"height":14,"pixelRatio":1,"width":23,"x":388,"y":319},"white_old_shield_4":{"height":14,"pixelRatio":1,"width":27,"x":352,"y":82},"white_old_shield_5":{"height":14,"pixelRatio":1,"width":32,"x":181,"y":118},"white_old_shield_6":{"height":14,"pixelRatio":1,"width":37,"x":103,"y":58},"white_purple_1":{"height":14,"pixelRatio":1,"width":14,"x":342,"y":467},"white_purple_2":{"height":14,"pixelRatio":1,"width":18,"x":429,"y":411},"white_purple_3":{"height":14,"pixelRatio":1,"width":23,"x":388,"y":303},"white_purple_4":{"height":14,"pixelRatio":1,"width":27,"x":323,"y":82},"white_purple_5":{"height":14,"pixelRatio":1,"width":32,"x":147,"y":118},"white_purple_6":{"height":14,"pixelRatio":1,"width":37,"x":42,"y":296},"white_qat_shield_1":{"height":14,"pixelRatio":1,"width":14,"x":373,"y":438},"white_qat_shield_2":{"height":14,"pixelRatio":1,"width":18,"x":409,"y":425},"white_qat_shield_3":{"height":14,"pixelRatio":1,"width":23,"x":388,"y":335},"white_qat_shield_4":{"height":14,"pixelRatio":1,"width":27,"x":322,"y":98},"white_qat_shield_5":{"height":14,"pixelRatio":1,"width":32,"x":244,"y":119},"white_qat_shield_6":{"height":14,"pixelRatio":1,"width":37,"x":103,"y":74},"white_red_1":{"height":14,"pixelRatio":1,"width":14,"x":342,"y":467},"white_red_2":{"height":14,"pixelRatio":1,"width":18,"x":429,"y":411},"white_red_3":{"height":14,"pixelRatio":1,"width":23,"x":388,"y":303},"white_red_4":{"height":14,"pixelRatio":1,"width":27,"x":323,"y":82},"white_red_5":{"height":14,"pixelRatio":1,"width":32,"x":147,"y":118},"white_red_6":{"height":14,"pixelRatio":1,"width":37,"x":42,"y":296},"white_rnd_shield_1":{"height":14,"pixelRatio":1,"width":11,"x":485,"y":413},"white_rnd_shield_2":{"height":14,"pixelRatio":1,"width":15,"x":481,"y":280},"white_rnd_shield_3":{"height":14,"pixelRatio":1,"width":19,"x":395,"y":255},"white_rnd_shield_4":{"height":14,"pixelRatio":1,"width":23,"x":437,"y":299},"white_rnd_shield_5":{"height":14,"pixelRatio":1,"width":27,"x":351,"y":98},"white_rnd_shield_6":{"height":14,"pixelRatio":1,"width":31,"x":277,"y":150},"white_rnd_star_1":{"height":14,"pixelRatio":1,"width":13,"x":475,"y":461},"white_rnd_star_2":{"height":14,"pixelRatio":1,"width":18,"x":429,"y":427},"white_rnd_star_3":{"height":14,"pixelRatio":1,"width":22,"x":388,"y":287},"white_rnd_star_4":{"height":14,"pixelRatio":1,"width":27,"x":322,"y":114},"white_rnd_star_5":{"height":14,"pixelRatio":1,"width":31,"x":148,"y":150},"white_rnd_star_6":{"height":14,"pixelRatio":1,"width":36,"x":142,"y":70},"white_shield_1":{"height":14,"pixelRatio":1,"width":10,"x":432,"y":475},"white_shield_2":{"height":14,"pixelRatio":1,"width":14,"x":389,"y":447},"white_shield_3":{"height":14,"pixelRatio":1,"width":17,"x":470,"y":397},"white_shield_4":{"height":14,"pixelRatio":1,"width":21,"x":413,"y":329},"white_shield_5":{"height":14,"pixelRatio":1,"width":25,"x":407,"y":91},"white_shield_6":{"height":14,"pixelRatio":1,"width":28,"x":323,"y":66},"white_sixtangle_1":{"height":14,"pixelRatio":1,"width":14,"x":373,"y":454},"white_sixtangle_2":{"height":14,"pixelRatio":1,"width":18,"x":389,"y":431},"white_sixtangle_3":{"height":14,"pixelRatio":1,"width":23,"x":436,"y":315},"white_sixtangle_4":{"height":14,"pixelRatio":1,"width":27,"x":351,"y":114},"white_sixtangle_5":{"height":14,"pixelRatio":1,"width":32,"x":278,"y":118},"white_sixtangle_6":{"height":14,"pixelRatio":1,"width":37,"x":142,"y":38},"white_square_bkbrd_1":{"height":14,"pixelRatio":1,"width":14,"x":373,"y":470},"white_square_bkbrd_2":{"height":14,"pixelRatio":1,"width":18,"x":449,"y":432},"white_square_bkbrd_3":{"height":14,"pixelRatio":1,"width":22,"x":413,"y":297},"white_square_bkbrd_4":{"height":14,"pixelRatio":1,"width":27,"x":408,"y":43},"white_square_bkbrd_5":{"height":14,"pixelRatio":1,"width":31,"x":181,"y":150},"white_square_bkbrd_6":{"height":14,"pixelRatio":1,"width":35,"x":180,"y":70},"yellow_penta_1":{"height":14,"pixelRatio":1,"width":12,"x":418,"y":475},"yellow_penta_2":{"height":14,"pixelRatio":1,"width":17,"x":409,"y":441},"yellow_penta_3":{"height":14,"pixelRatio":1,"width":21,"x":413,"y":345},"yellow_penta_4":{"height":14,"pixelRatio":1,"width":25,"x":434,"y":99},"yellow_penta_5":{"height":14,"pixelRatio":1,"width":29,"x":202,"y":399},"yellow_penta_6":{"height":14,"pixelRatio":1,"width":33,"x":437,"y":19},"yellow_penta_cap_1":{"height":14,"pixelRatio":1,"width":8,"x":278,"y":87},"yellow_penta_cap_2":{"height":14,"pixelRatio":1,"width":11,"x":444,"y":464},"yellow_penta_cap_3":{"height":14,"pixelRatio":1,"width":13,"x":418,"y":459},"yellow_penta_cap_4":{"height":14,"pixelRatio":1,"width":16,"x":480,"y":365},"yellow_penta_cap_5":{"height":14,"pixelRatio":1,"width":19,"x":416,"y":265},"yellow_penta_cap_6":{"height":14,"pixelRatio":1,"width":21,"x":436,"y":347},"yellow_sixtangle_1":{"height":14,"pixelRatio":1,"width":11,"x":457,"y":464},"yellow_sixtangle_2":{"height":14,"pixelRatio":1,"width":15,"x":481,"y":296},"yellow_sixtangle_3":{"height":14,"pixelRatio":1,"width":19,"x":459,"y":352},"yellow_sixtangle_4":{"height":14,"pixelRatio":1,"width":23,"x":436,"y":331},"yellow_sixtangle_5":{"height":14,"pixelRatio":1,"width":27,"x":406,"y":59},"yellow_sixtangle_6":{"height":14,"pixelRatio":1,"width":31,"x":244,"y":151},"zoo-11":{"height":19,"pixelRatio":1,"width":19,"x":349,"y":367},"zoo-15":{"height":23,"pixelRatio":1,"width":23,"x":207,"y":191}}
